dddm/__init__.py
dddm/context.py
dddm/priors.py
dddm/statistics.py
dddm/test_utils.py
dddm/utils.py
dddm/detectors/__init__.py
dddm/detectors/examples.py
dddm/detectors/experiment.py
dddm/detectors/lindhard_factors.py
dddm/detectors/super_cdms.py
dddm/detectors/super_cdms_darkelf.py
dddm/detectors/xenon_nt.py
dddm/plotting/__init__.py
dddm/plotting/confidence_figures.py
dddm/plotting/plot_basics.py
dddm/plotting/seaborn_utils.py
dddm/recoil_rates/__init__.py
dddm/recoil_rates/detector_spectrum.py
dddm/recoil_rates/halo.py
dddm/recoil_rates/halo_shielded.py
dddm/recoil_rates/spectrum.py
dddm/samplers/__init__.py
dddm/samplers/emcee.py
dddm/samplers/multi_detectors.py
dddm/samplers/nestle.py
dddm/samplers/pymultinest.py
dddm/samplers/ultranest.py
dddm-4.0.0.data/scripts/run_combined_multinest
dddm-4.0.0.data/scripts/run_dddm_emcee
extra_requirements/requirements-tests.txt
tests/__init__.py
tests/test_1d_likelihood.py
tests/test_bin.py
tests/test_context.py
tests/test_depricated.py
tests/test_experiment_class.py
tests/test_plots.py
tests/test_seaborn_utils.py
tests/test_several.py
tests/test_smearing.py
tests/test_spectra.py
tests/test_spectrum_generation.py
tests/test_utils.py
tests/test_samplers/__init__.py
tests/test_samplers/test_emcee.py
tests/test_samplers/test_multinest.py
tests/test_samplers/test_nestle.py
tests/test_samplers/test_ultranest.py
dddm-4.0.0.dist-info/LICENSE
dddm-4.0.0.dist-info/METADATA
dddm-4.0.0.dist-info/WHEEL
dddm-4.0.0.dist-info/top_level.txt
dddm-4.0.0.dist-info/RECORD
