Metadata-Version: 2.1
Name: dddm
Version: 4.0.0
Summary: Direct Detection of Dark Matter: Probing the complementarity of several targets for dark matter detection
Home-page: https://github.com/jorana/DD_DM_targets
Author: Joran R. Angevaare
License: UNKNOWN
Keywords: todo
Platform: UNKNOWN
Classifier: Intended Audience :: Science/Research
Classifier: Development Status :: 3 - Alpha
Classifier: Programming Language :: Python :: 3.8
Classifier: Natural Language :: English
Classifier: Programming Language :: Python :: 3.8
Classifier: Programming Language :: Python :: 3.9
Classifier: Programming Language :: Python :: 3.10
Classifier: Intended Audience :: Science/Research
Classifier: Programming Language :: Python :: Implementation :: CPython
Classifier: Topic :: Scientific/Engineering :: Physics
Requires-Python: >=3.8
Requires-Dist: corner
Requires-Dist: coveralls
Requires-Dist: emcee
Requires-Dist: h5py
Requires-Dist: hypothesis
Requires-Dist: immutabledict
Requires-Dist: matplotlib
Requires-Dist: multihist
Requires-Dist: nestle
Requires-Dist: numba
Requires-Dist: numericalunits
Requires-Dist: numpy
Requires-Dist: pandas
Requires-Dist: pytest
Requires-Dist: pytest-runner
Requires-Dist: scipy
Requires-Dist: seaborn (~=0.11.2)
Requires-Dist: tqdm
Requires-Dist: ultranest
